statute_patterns/__init__.py
statute_patterns/__main__.py
statute_patterns/components/__init__.py
statute_patterns/components/category.py
statute_patterns/components/details.py
statute_patterns/components/rule.py
statute_patterns/components/short.py
statute_patterns/components/utils.py
statute_patterns/models.py
statute_patterns/names.py
statute_patterns/recipes/__init__.py
statute_patterns/recipes/const.py
statute_patterns/recipes/digits.py
statute_patterns/recipes/roc.py
statute_patterns/recipes/spain.py
statute_patterns/serials.py
statute_patterns-0.2.5.dist-info/LICENSE
statute_patterns-0.2.5.dist-info/METADATA
statute_patterns-0.2.5.dist-info/WHEEL
statute_patterns-0.2.5.dist-info/RECORD
