Metadata-Version: 2.1
Name: statute-patterns
Version: 0.2.5
Summary: Philippine statutory law pattern matching and unit retrieval.
Home-page: https://lawsql.com
Author: Marcelino G. Veloso III
Author-email: mars@veloso.one
Requires-Python: >=3.11,<4.0
Classifier: Development Status :: 4 - Beta
Classifier: Framework :: Pydantic
Classifier: Framework :: Pytest
Classifier: Intended Audience :: Legal Industry
Classifier: Programming Language :: Python :: 3
Classifier: Programming Language :: Python :: 3.11
Classifier: Programming Language :: Python :: 3.11
Classifier: Typing :: Typed
Requires-Dist: email-validator (>=2.0.0.post2,<3.0.0)
Requires-Dist: pydantic (>=1.10.7,<2.0.0)
Requires-Dist: python-dateutil (>=2.8.2,<3.0.0)
Requires-Dist: python-dotenv (>=1.0,<2.0)
Requires-Dist: python-slugify (>=8.0,<9.0)
Project-URL: Documentation, https://justmars.github.io/statute-patterns
Project-URL: Repository, https://github.com/justmars/statute-patterns
